stDCL/_init_.py
stDCL/model.py
stDCL/preprocess.py
stDCL/stDCL.py
stDCL/utils.py
stDCL-1.0.1.dist-info/LICENSE
stDCL-1.0.1.dist-info/METADATA
stDCL-1.0.1.dist-info/WHEEL
stDCL-1.0.1.dist-info/top_level.txt
stDCL-1.0.1.dist-info/RECORD
