Metadata-Version: 2.1
Name: stDCL
Version: 1.0.1
Summary: Spatial Transcriptome Heterogeneity Dissection of Brain Regions with Dual Graph Contrastive Learning
Home-page: https://github.com/Philyzh8/stDCL
Author: Zhuohan Yu
Author-email: zhuohan20@mails.jlu.edu.cn
License: MIT
Platform: UNKNOWN
Classifier: Operating System :: OS Independent
Classifier: Topic :: Scientific/Engineering :: Artificial Intelligence
Classifier: Programming Language :: Python :: 3.8
License-File: LICENSE
